angst/__init__.py
angst/_points.py
angst/_version.py
angst/test/conftest.py
angst/test/test_points.py
angst-0.0.1.dist-info/METADATA
angst-0.0.1.dist-info/WHEEL
angst-0.0.1.dist-info/licenses/LICENSE
angst-0.0.1.dist-info/RECORD
